pandas_ta_remake/__init__.py
pandas_ta_remake/core.py
pandas_ta_remake/custom.py
pandas_ta_remake/candles/__init__.py
pandas_ta_remake/candles/cdl_doji.py
pandas_ta_remake/candles/cdl_inside.py
pandas_ta_remake/candles/cdl_pattern.py
pandas_ta_remake/candles/cdl_z.py
pandas_ta_remake/candles/ha.py
pandas_ta_remake/cycles/__init__.py
pandas_ta_remake/cycles/ebsw.py
pandas_ta_remake/momentum/__init__.py
pandas_ta_remake/momentum/ao.py
pandas_ta_remake/momentum/apo.py
pandas_ta_remake/momentum/bias.py
pandas_ta_remake/momentum/bop.py
pandas_ta_remake/momentum/brar.py
pandas_ta_remake/momentum/cci.py
pandas_ta_remake/momentum/cfo.py
pandas_ta_remake/momentum/cg.py
pandas_ta_remake/momentum/cmo.py
pandas_ta_remake/momentum/coppock.py
pandas_ta_remake/momentum/cti.py
pandas_ta_remake/momentum/dm.py
pandas_ta_remake/momentum/er.py
pandas_ta_remake/momentum/eri.py
pandas_ta_remake/momentum/fisher.py
pandas_ta_remake/momentum/inertia.py
pandas_ta_remake/momentum/kdj.py
pandas_ta_remake/momentum/kst.py
pandas_ta_remake/momentum/macd.py
pandas_ta_remake/momentum/mom.py
pandas_ta_remake/momentum/pgo.py
pandas_ta_remake/momentum/ppo.py
pandas_ta_remake/momentum/psl.py
pandas_ta_remake/momentum/pvo.py
pandas_ta_remake/momentum/qqe.py
pandas_ta_remake/momentum/roc.py
pandas_ta_remake/momentum/rsi.py
pandas_ta_remake/momentum/rsx.py
pandas_ta_remake/momentum/rvgi.py
pandas_ta_remake/momentum/slope.py
pandas_ta_remake/momentum/smi.py
pandas_ta_remake/momentum/squeeze.py
pandas_ta_remake/momentum/squeeze_pro.py
pandas_ta_remake/momentum/stc.py
pandas_ta_remake/momentum/stoch.py
pandas_ta_remake/momentum/stochrsi.py
pandas_ta_remake/momentum/td_seq.py
pandas_ta_remake/momentum/trix.py
pandas_ta_remake/momentum/tsi.py
pandas_ta_remake/momentum/uo.py
pandas_ta_remake/momentum/willr.py
pandas_ta_remake/overlap/__init__.py
pandas_ta_remake/overlap/alma.py
pandas_ta_remake/overlap/dema.py
pandas_ta_remake/overlap/ema.py
pandas_ta_remake/overlap/fwma.py
pandas_ta_remake/overlap/hilo.py
pandas_ta_remake-1.0.4.dist-info/METADATA
pandas_ta_remake-1.0.4.dist-info/WHEEL
pandas_ta_remake-1.0.4.dist-info/licenses/LICENSE
pandas_ta_remake-1.0.4.dist-info/RECORD
