Metadata-Version: 2.4
Name: pandas-ta-remake
Version: 1.0.4
Summary: Technical Analysis Indicators - Pandas TA is an easy to use Python 3 Pandas Extension with 150+ Indicators
Project-URL: Repository, https://github.com/osama-dev-repo/pandas-ta
License: The MIT License (MIT)
License-File: LICENSE
Requires-Python: >=3.11
Requires-Dist: numpy==2.2.1
Requires-Dist: pandas==2.2.3
Requires-Dist: python-dateutil==2.9.0.post0
Requires-Dist: pytz==2024.2
Requires-Dist: setuptools
Requires-Dist: six==1.17.0
Requires-Dist: tzdata==2024.2
